README.md
setup.py
metric_client/__init__.py
metric_client/client.py
metric_client.egg-info/PKG-INFO
metric_client.egg-info/SOURCES.txt
metric_client.egg-info/dependency_links.txt
metric_client.egg-info/requires.txt
metric_client.egg-info/top_level.txt
metric_client/../README.md