Metadata-Version: 1.1
Name: metric-client
Version: 1.1.0
Summary: metric client for python
Home-page: https://github.com/zskymn/metric-client-py
Author: zskymn
Author-email: zsymn@163.com
License: MIT
Platform: UNKNOWN
Classifier: Development Status :: 3 - Alpha
Classifier: Intended Audience :: Developers
Classifier: Topic :: Scientific/Engineering
Classifier: License :: OSI Approved :: MIT License
Classifier: Programming Language :: Python :: 2.7
Classifier: Programming Language :: Python :: 3.5
